defloat.py
DeFloat-0.0.1.dist-info/LICENSE
DeFloat-0.0.1.dist-info/METADATA
DeFloat-0.0.1.dist-info/WHEEL
DeFloat-0.0.1.dist-info/top_level.txt
DeFloat-0.0.1.dist-info/RECORD
