Metadata-Version: 2.1
Name: DeFloat
Version: 0.0.1
Summary: Portable Floating Point Decomposition
Home-page: https://github.com/technikker/defloat
Author: techniker
Author-email: <mail@xxxxxxxx.com>
License: MPL
Project-URL: Source, https://github.com/technikker/defloat
Keywords: python,DeFloat,float,floating,point,decompose,decomposition,portable
Classifier: Development Status :: 4 - Beta
Classifier: Intended Audience :: Developers
Classifier: License :: OSI Approved :: Mozilla Public License 2.0 (MPL 2.0)
Classifier: Programming Language :: Python :: 3
Classifier: Programming Language :: Python :: 3.6
Classifier: Programming Language :: Python :: 3.7
Classifier: Programming Language :: Python :: 3.8
Classifier: Programming Language :: Python :: 3.9
Classifier: Programming Language :: Python :: 3.10
Classifier: Programming Language :: Python :: 3.11
Classifier: Programming Language :: Python :: 3.12
Classifier: Operating System :: OS Independent
Classifier: Topic :: Software Development :: Embedded Systems
Classifier: Topic :: Scientific/Engineering
Classifier: Topic :: Utilities
License-File: LICENSE
